plone_sphinx_theme/__init__.py
plone_sphinx_theme/assets/scripts/index.js
plone_sphinx_theme/assets/styles/index.scss
plone_sphinx_theme/assets/styles/abstracts/_links.scss
plone_sphinx_theme/assets/styles/abstracts/_mixins.scss
plone_sphinx_theme/assets/styles/components/_icon-links.scss
plone_sphinx_theme/assets/styles/components/_title.scss
plone_sphinx_theme/assets/styles/components/_versionmodified.scss
plone_sphinx_theme/assets/styles/content/_admonitions.scss
plone_sphinx_theme/assets/styles/content/_code.scss
plone_sphinx_theme/assets/styles/content/_images.scss
plone_sphinx_theme/assets/styles/content/_lists.scss
plone_sphinx_theme/assets/styles/content/_spans.scss
plone_sphinx_theme/assets/styles/extensions/_tippy.scss
plone_sphinx_theme/assets/styles/extensions/_todo.scss
plone_sphinx_theme/assets/styles/extensions/_video.scss
plone_sphinx_theme/assets/styles/sphinx-book-theme/index.scss
plone_sphinx_theme/assets/styles/sphinx-book-theme/abstracts/_mixins.scss
plone_sphinx_theme/assets/styles/sphinx-book-theme/abstracts/_variables.scss
plone_sphinx_theme/assets/styles/sphinx-book-theme/base/_base.scss
plone_sphinx_theme/assets/styles/sphinx-book-theme/base/_print.scss
plone_sphinx_theme/assets/styles/sphinx-book-theme/base/_typography.scss
plone_sphinx_theme/assets/styles/sphinx-book-theme/components/_back-to-top.scss
plone_sphinx_theme/assets/styles/sphinx-book-theme/components/_icon-links.scss
plone_sphinx_theme/assets/styles/sphinx-book-theme/components/_logo.scss
plone_sphinx_theme/assets/styles/sphinx-book-theme/components/_search.scss
plone_sphinx_theme/assets/styles/sphinx-book-theme/content/_code.scss
plone_sphinx_theme/assets/styles/sphinx-book-theme/content/_images.scss
plone_sphinx_theme/assets/styles/sphinx-book-theme/content/_margin.scss
plone_sphinx_theme/assets/styles/sphinx-book-theme/content/_notebooks.scss
plone_sphinx_theme/assets/styles/sphinx-book-theme/content/_quotes.scss
plone_sphinx_theme-1.4.3.dist-info/LICENSE
plone_sphinx_theme-1.4.3.dist-info/METADATA
plone_sphinx_theme-1.4.3.dist-info/WHEEL
plone_sphinx_theme-1.4.3.dist-info/entry_points.txt
plone_sphinx_theme-1.4.3.dist-info/top_level.txt
plone_sphinx_theme-1.4.3.dist-info/RECORD
