Metadata-Version: 2.2
Name: plone-sphinx-theme
Version: 1.4.3
Summary: Plone Sphinx Theme is the official Sphinx theme for Plone 6 Documentation, Plone Conference Training, and documentation of various Plone packages.
Author-email: Steve Piercy <spiercy@plone.org>
Maintainer-email: Steve Piercy <spiercy@plone.org>
License:                     GNU GENERAL PUBLIC LICENSE
Project-URL: Documentation, https://plone-sphinx-theme.readthedocs.io/
Project-URL: Repository, https://github.com/plone/plone-sphinx-theme
Project-URL: Issues, https://github.com/plone/plone-sphinx-theme/issues
Project-URL: Changelog, https://github.com/plone/plone-sphinx-theme/blob/main/CHANGES.md
Project-URL: Sponsor, https://github.com/sponsors/plone
Project-URL: Discord, https://discord.com/channels/786421998426521600/862642144401031188
Project-URL: Mastodon, https://plone.social/@plone
Project-URL: YouTube, https://www.youtube.com/@plonecms
Keywords: Plone,Sphinx,Theme,documentation,training,Diátaxis
Classifier: Development Status :: 5 - Production/Stable
Classifier: Framework :: Sphinx
Classifier: Framework :: Sphinx :: Theme
Classifier: License :: OSI Approved :: GNU General Public License v2 (GPLv2)
Classifier: Operating System :: OS Independent
Classifier: Programming Language :: Python
Classifier: Programming Language :: Python :: 3
Classifier: Programming Language :: Python :: 3.10
Classifier: Programming Language :: Python :: 3.11
Classifier: Programming Language :: Python :: 3.12
Classifier: Programming Language :: Python :: 3.13
Requires-Python: <3.14,>=3.10
License-File: LICENSE
Requires-Dist: myst-parser
Requires-Dist: sphinx-book-theme==1.1.4
